webpowerpy
